{
  "resource_uri": "https://www.courtlistener.com/api/rest/v3/opinions/131414/",
  "id": 131414,
  "absolute_url": "/opinion/131414/cohen-v-united-states/",
  "cluster": "https://www.courtlistener.com/api/rest/v3/clusters/131414/",
  "author": null,
  "joined_by": [],
  "author_str": "",
  "per_curiam": false,
  "date_created": "2010-04-28T17:27:32Z",
  "date_modified": "2017-03-24T06:21:02.401635Z",
  "type": "010combined",
  "sha1": "6f861f8a8eb6a64218a75f55afadf74b95685038",
  "page_count": null,
  "download_url": "http://bulk.resource.org/courts.gov/c/US/540/540.US.821.02-1777.html",
  "local_path": null,
  "plain_text": "",
  "html": "<p class=\"case_cite\">540 U.S. 821</p>\n    <p class=\"parties\">COHEN<br>v.<br>UNITED STATES.</p>\n    <p class=\"docket\">No. 02-1777.</p>\n    <p class=\"court\">Supreme Court of United States.</p>\n    <p class=\"date\">October 6, 2003.</p>\n    <div class=\"num\" id=\"p1\">\n      <span class=\"num\">1</span>\n      <p class=\"indent\">Appeal from the C. A. 11th Cir.</p>\n    </div>\n    <div class=\"num\" id=\"p2\">\n      <span class=\"num\">2</span>\n      <p class=\"indent\">Certiorari denied. Reported below: 49 Fed. Appx. 287.</p>\n    </div>\n    ",
  "html_lawbox": "",
  "html_columbia": null,
  "html_with_citations": "<p class=\"case_cite\"><span class=\"citation no-link\"><span class=\"volume\">540</span> <span class=\"reporter\">U.S.</span> <span class=\"page\">821</span></span></p>\n    <p class=\"parties\">COHEN<br>v.<br>UNITED STATES.</p>\n    <p class=\"docket\">No. 02-1777.</p>\n    <p class=\"court\">Supreme Court of United States.</p>\n    <p class=\"date\">October 6, 2003.</p>\n    <div class=\"num\" id=\"p1\">\n      <span class=\"num\">1</span>\n      <p class=\"indent\">Appeal from the C. A. 11th Cir.</p>\n    </div>\n    <div class=\"num\" id=\"p2\">\n      <span class=\"num\">2</span>\n      <p class=\"indent\">Certiorari denied. Reported below: 49 Fed. Appx. 287.</p>\n    </div>\n    ",
  "extracted_by_ocr": false,
  "opinions_cited": []
}